[
    {
        "ilce_id": "1131",
        "ilce_adi": "Altınözü",
        "ilce_slug": "altinozu"
    },
    {
        "ilce_id": "1289",
        "ilce_adi": "Dörtyol",
        "ilce_slug": "dortyol"
    },
    {
        "ilce_id": "1382",
        "ilce_adi": "Hassa",
        "ilce_slug": "hassa"
    },
    {
        "ilce_id": "1413",
        "ilce_adi": "İskenderun",
        "ilce_slug": "iskenderun"
    },
    {
        "ilce_id": "1468",
        "ilce_adi": "Kırıkhan",
        "ilce_slug": "kirikhan"
    },
    {
        "ilce_id": "1585",
        "ilce_adi": "Reyhanlı",
        "ilce_slug": "reyhanli"
    },
    {
        "ilce_id": "1591",
        "ilce_adi": "Samandağ",
        "ilce_slug": "samandag"
    },
    {
        "ilce_id": "1721",
        "ilce_adi": "Yayladağı",
        "ilce_slug": "yayladagi"
    },
    {
        "ilce_id": "1792",
        "ilce_adi": "Erzin",
        "ilce_slug": "erzin"
    },
    {
        "ilce_id": "1887",
        "ilce_adi": "Belen",
        "ilce_slug": "belen"
    },
    {
        "ilce_id": "1970",
        "ilce_adi": "Kumlu",
        "ilce_slug": "kumlu"
    },
    {
        "ilce_id": "2080",
        "ilce_adi": "Antakya",
        "ilce_slug": "antakya"
    },
    {
        "ilce_id": "2081",
        "ilce_adi": "Arsuz",
        "ilce_slug": "arsuz"
    },
    {
        "ilce_id": "2082",
        "ilce_adi": "Defne",
        "ilce_slug": "defne"
    },
    {
        "ilce_id": "2083",
        "ilce_adi": "Payas",
        "ilce_slug": "payas"
    }
]