[
    {
        "ilce_id": "1170",
        "ilce_adi": "Banaz",
        "ilce_slug": "banaz"
    },
    {
        "ilce_id": "1323",
        "ilce_adi": "Eşme",
        "ilce_slug": "esme"
    },
    {
        "ilce_id": "1436",
        "ilce_adi": "Karahallı",
        "ilce_slug": "karahalli"
    },
    {
        "ilce_id": "1629",
        "ilce_adi": "Sivaslı",
        "ilce_slug": "sivasli"
    },
    {
        "ilce_id": "1697",
        "ilce_adi": "Ulubey",
        "ilce_slug": "ulubey"
    },
    {
        "ilce_id": "1704",
        "ilce_adi": "Merkez",
        "ilce_slug": "merkez"
    }
]